pydantic_ai_arcade/__init__.py
pydantic_ai_arcade/_errors.py
pydantic_ai_arcade/_tools.py
pydantic_ai_arcade/_utils.py
pydantic_ai_arcade/py.typed
pydantic_ai_arcade-0.1.0.dist-info/WHEEL
pydantic_ai_arcade-0.1.0.dist-info/METADATA
pydantic_ai_arcade-0.1.0.dist-info/RECORD
