Metadata-Version: 2.3
Name: pydantic-ai-arcade
Version: 0.1.0
Summary: Arcade integration for Pydantic AI
Author: Tho Nguyen
Author-email: Tho Nguyen <contact@naiwaaa.simplelogin.com>
License: MIT License
Classifier: Intended Audience :: Developers
Classifier: Intended Audience :: Information Technology
Classifier: License :: OSI Approved :: MIT License
Classifier: Operating System :: OS Independent
Classifier: Programming Language :: Python
Classifier: Programming Language :: Python :: 3
Classifier: Programming Language :: Python :: 3 :: Only
Classifier: Programming Language :: Python :: 3.10
Classifier: Programming Language :: Python :: 3.11
Classifier: Programming Language :: Python :: 3.12
Classifier: Programming Language :: Python :: 3.13
Classifier: Programming Language :: Python :: 3.14
Classifier: Topic :: Software Development :: Libraries :: Python Modules
Classifier: Typing :: Typed
Requires-Dist: arcadepy>=1.5.0
Requires-Dist: pydantic-ai-slim>=1.45.0
Requires-Python: >=3.10
Project-URL: Homepage, https://codeberg.org/naiwaaa/pydantic-ai-arcade
Project-URL: Documentation, https://codeberg.org/naiwaaa/pydantic-ai-arcade
Project-URL: Repository, https://codeberg.org/naiwaaa/pydantic-ai-arcade
Project-URL: Issues, https://codeberg.org/naiwaaa/pydantic-ai-arcade/issues
